[
    {
        "key": "dbln",
        "value": "%7B%22100066570006324%22%3A%22aG6decpD%22%2C%22100089614921989%22%3A%225Sfro2Dn%22%2C%2261551611357804%22%3A%22SMrQiaBY%22%2C%2261552313656358%22%3A%225IQJ3svn%22%2C%22100022226183366%22%3A%22IW41uIz3%22%2C%2261552397676313%22%3A%221Jb0zMYJ%22%2C%2261553287075944%22%3A%22a6r5xKH8%22%2C%2261552592532032%22%3A%22XkAxM9Cb%22%2C%22100023988141484%22%3A%22inu0AV1q%22%2C%2261554827459908%22%3A%22qjDXe4xT%22%2C%2261554339315396%22%3A%22DoW87SLx%22%2C%22100080409855375%22%3A%221zdCBc2Z%22%2C%2261555842300876%22%3A%22oYsxvnER%22%2C%22100092271272159%22%3A%22xEGb5TSn%22%2C%22100000158407576%22%3A%22UgloaUPm%22%2C%22100090810596085%22%3A%22R4f0j0T4%22%7D",
        "domain": "facebook.com",
        "path": "/login/device-based/",
        "hostOnly": false,
        "creation": "2024-05-24T04:43:22.394Z",
        "lastAccessed": "2024-05-24T04:43:22.394Z"
    },
    {
        "key": "datr",
        "value": "gIVPZtZfH7QdFJhdLAm7NOvK",
        "domain": "facebook.com",
        "path": "/",
        "hostOnly": false,
        "creation": "2024-05-24T04:43:22.394Z",
        "lastAccessed": "2024-05-24T04:43:22.394Z"
    },
    {
        "key": "sb",
        "value": "gIVPZiyJ6WOrh2rk1hsiFBwu",
        "domain": "facebook.com",
        "path": "/",
        "hostOnly": false,
        "creation": "2024-05-24T04:43:22.394Z",
        "lastAccessed": "2024-05-24T04:43:22.394Z"
    },
    {
        "key": "locale",
        "value": "en_GB",
        "domain": "facebook.com",
        "path": "/",
        "hostOnly": false,
        "creation": "2024-05-24T04:43:22.394Z",
        "lastAccessed": "2024-05-24T04:43:22.394Z"
    },
    {
        "key": "vpd",
        "value": "v1%3B720x393x2.75",
        "domain": "facebook.com",
        "path": "/",
        "hostOnly": false,
        "creation": "2024-05-24T04:43:22.394Z",
        "lastAccessed": "2024-05-24T04:43:22.394Z"
    },
    {
        "key": "m_pixel_ratio",
        "value": "2.75",
        "domain": "facebook.com",
        "path": "/",
        "hostOnly": false,
        "creation": "2024-05-24T04:43:22.394Z",
        "lastAccessed": "2024-05-24T04:43:22.394Z"
    },
    {
        "key": "wd",
        "value": "393x720",
        "domain": "facebook.com",
        "path": "/",
        "hostOnly": false,
        "creation": "2024-05-24T04:43:22.394Z",
        "lastAccessed": "2024-05-24T04:43:22.394Z"
    },
    {
        "key": "fr",
        "value": "0DOEPFxQDgSJtmgvY.AWVsoo8Tb3ChfiJ5udRcgNmuJQ4.BmLUt9..AAA.0.0.BmUBqe.AWWWDqci9zg",
        "domain": "facebook.com",
        "path": "/",
        "hostOnly": false,
        "creation": "2024-05-24T04:43:22.394Z",
        "lastAccessed": "2024-05-24T04:43:22.394Z"
    },
    {
        "key": "c_user",
        "value": "100092271272159",
        "domain": "facebook.com",
        "path": "/",
        "hostOnly": false,
        "creation": "2024-05-24T04:43:22.394Z",
        "lastAccessed": "2024-05-24T04:43:22.394Z"
    },
    {
        "key": "xs",
        "value": "41%3AybrvWUxZKN52ew%3A2%3A1716525727%3A-1%3A5166",
        "domain": "facebook.com",
        "path": "/",
        "hostOnly": false,
        "creation": "2024-05-24T04:43:22.394Z",
        "lastAccessed": "2024-05-24T04:43:22.394Z"
    },
    {
        "key": "ps_n",
        "value": "1",
        "domain": "facebook.com",
        "path": "/",
        "hostOnly": false,
        "creation": "2024-05-24T04:43:22.394Z",
        "lastAccessed": "2024-05-24T04:43:22.394Z"
    },
    {
        "key": "ps_l",
        "value": "1",
        "domain": "facebook.com",
        "path": "/",
        "hostOnly": false,
        "creation": "2024-05-24T04:43:22.394Z",
        "lastAccessed": "2024-05-24T04:43:22.394Z"
    },
    {
        "key": "fbl_st",
        "value": "101327705%3BT%3A28608762",
        "domain": "facebook.com",
        "path": "/",
        "hostOnly": false,
        "creation": "2024-05-24T04:43:22.394Z",
        "lastAccessed": "2024-05-24T04:43:22.394Z"
    },
    {
        "key": "wl_cbv",
        "value": "v2%3Bclient_version%3A2510%3Btimestamp%3A1716525731",
        "domain": "facebook.com",
        "path": "/",
        "hostOnly": false,
        "creation": "2024-05-24T04:43:22.394Z",
        "lastAccessed": "2024-05-24T04:43:22.394Z"
    }
]
